riann/__init__.py
riann/_modidx.py
riann/_nbdev.py
riann/riann.onnx
riann/riann.py
riann-0.1.3.dist-info/licenses/LICENSE
riann-0.1.3.dist-info/METADATA
riann-0.1.3.dist-info/WHEEL
riann-0.1.3.dist-info/entry_points.txt
riann-0.1.3.dist-info/top_level.txt
riann-0.1.3.dist-info/RECORD
