Metadata-Version: 2.4
Name: riann
Version: 0.1.3
Summary: A Neural Network for attitude estimation using IMU data
Home-page: https://github.com/daniel-om-weber/riann
Author: Daniel Oliver Martin Weber
Author-email: daniel.om.weber@gmail.com
License: Apache Software License 2.0
Keywords: AHRS,Neural Network,Attitude,IMU
Classifier: Development Status :: 3 - Alpha
Classifier: Intended Audience :: Developers
Classifier: Natural Language :: English
Classifier: Programming Language :: Python :: 3.9
Classifier: Programming Language :: Python :: 3.10
Classifier: License :: OSI Approved :: Apache Software License
Requires-Python: >=3.9
License-File: LICENSE
Requires-Dist: onnxruntime
Requires-Dist: packaging
Provides-Extra: dev
Requires-Dist: nbdev>2; extra == "dev"
Requires-Dist: matplotlib; extra == "dev"
Requires-Dist: h5py; extra == "dev"
Dynamic: author
Dynamic: author-email
Dynamic: classifier
Dynamic: description
Dynamic: description-content-type
Dynamic: home-page
Dynamic: keywords
Dynamic: license
Dynamic: license-file
Dynamic: provides-extra
Dynamic: requires-dist
Dynamic: requires-python
Dynamic: summary
